{"type": "Feature", "id": 12511819, "geometry": {"type": "Point", "coordinates": [-78.828697, 48.21349]}, "properties": {"woe:id": 12511819, "woe:parent_id": 958, "woe:name": "A\u00e9roport de Rouyn-Noranda", "woe:placetype": 14, "woe:placetype_name": "Airport", "woe:lang": "FRE", "iso:country": "CA", "meta:provider": ["geoplanet:7.3.1", "geoplanet:7.3.2", "geoplanet:7.4.0", "geoplanet:7.4.1", "geoplanet:7.5.1", "geoplanet:7.5.2", "geoplanet:7.6.0", "geoplanet:7.8.1", "geoplanet:7.9.0", "geoplanet:7.10.0", "geoplanet:8.0.0", "woeplanet:8.0.0"], "meta:indexed": "2020-08-20T20:29:28.588531", "woe:alias_ENG_V": ["YUY", "YUY Airport"], "meta:updated": "2020-10-14T12:10:35.372467", "woe:alias_ENG_P": ["Rouyn Noranda Airport"], "woe:alias_FRE_S": ["Aeroport de Rouyn-Noranda"], "woe:hierarchy": {"continent": 24865672, "country": 23424775, "town": 0, "planet": 1, "county": 29375240, "suburb": 0, "state": 2344924, "region": 0, "localadmin": 0}, "woe:timezone_id": 56043679, "woe:hash": "f0xfq0yxyjzq", "woe:centroid": [-78.828697, 48.21349], "geom:latitude": 48.21349, "geom:longitude": -78.828697, "geom:hash": "f0xfq0yxyjzq", "woe:latitude": 48.21349, "geom:centroid": [-78.828697, 48.21349], "woe:longitude": -78.828697, "woe:repo": "woeplanet-airport-ca", "geom:area": 0.0, "woe:scale": 19}}