{"type": "Feature", "id": 12511761, "properties": {"woe:id": 12511761, "woe:parent_id": 23403233, "woe:name": "Moose Jaw Airport", "woe:placetype": 14, "woe:placetype_name": "Airport", "woe:lang": "ENG", "iso:country": "CA", "meta:provider": ["geoplanet:7.3.1", "geoplanet:7.3.2", "geoplanet:7.4.0", "geoplanet:7.4.1", "geoplanet:7.5.1", "geoplanet:7.5.2", "geoplanet:7.6.0", "geoplanet:7.8.1", "geoplanet:7.9.0", "geoplanet:7.10.0", "geoplanet:8.0.0", "woeplanet:8.0.0"], "meta:indexed": "2020-08-20T20:29:28.279173", "woe:alias_ENG_V": ["YMJ", "YMJ Airport"], "meta:updated": "2020-08-22T02:31:16.509734", "woe:hierarchy": {"continent": 24865672, "country": 23424775, "town": 0, "planet": 1, "county": 29375232, "suburb": 0, "state": 2344925, "region": 0, "localadmin": 0}, "woe:timezone_id": 56043687, "woe:hash": "c8uymfq1s2qs", "woe:centroid": [-105.559196, 50.330002], "geom:latitude": 50.330002, "geom:longitude": -105.559196, "geom:hash": "c8uymfq1s2qs", "woe:latitude": 50.330002, "geom:centroid": [-105.559196, 50.330002], "woe:longitude": -105.559196, "woe:repo": "woeplanet-airport-ca"}, "geometry": {"coordinates": [-105.559196, 50.330002], "type": "Point"}}