{"type": "Feature", "id": 12511636, "geometry": {"type": "Point", "coordinates": [-65.786903, 44.549969]}, "properties": {"woe:id": 12511636, "woe:parent_id": 29374626, "woe:name": "Digby Municipal Airport", "woe:placetype": 14, "woe:placetype_name": "Airport", "woe:lang": "ENG", "iso:country": "CA", "meta:provider": ["geoplanet:7.3.1", "geoplanet:7.3.2", "geoplanet:7.4.0", "geoplanet:7.4.1", "geoplanet:7.5.1", "geoplanet:7.5.2", "geoplanet:7.6.0", "geoplanet:7.8.1", "geoplanet:7.9.0", "geoplanet:7.10.0", "geoplanet:8.0.0", "woeplanet:8.0.0"], "meta:indexed": "2020-08-20T20:29:28.663168", "woe:alias_ENG_V": ["YDG", "Digby Airport", "Digby Municipal", "YDG Airport"], "meta:updated": "2020-10-14T12:10:35.552167", "woe:hierarchy": {"continent": 24865672, "country": 23424775, "town": 0, "planet": 1, "county": 29375049, "suburb": 0, "state": 2344921, "region": 0, "localadmin": 0}, "woe:timezone_id": 56043685, "woe:hash": "dxcjqyp6qh1s", "woe:centroid": [-65.786903, 44.549969], "geom:latitude": 44.549969, "geom:longitude": -65.786903, "geom:hash": "dxcjqyp6qh1s", "woe:latitude": 44.549969, "geom:centroid": [-65.786903, 44.549969], "woe:longitude": -65.786903, "woe:repo": "woeplanet-airport-ca", "geom:area": 0.0, "woe:scale": 19}}