{"type": "Feature", "id": 12511678, "properties": {"woe:id": 12511678, "woe:parent_id": 9670, "woe:name": "Golden Airport", "woe:placetype": 14, "woe:placetype_name": "Airport", "woe:lang": "ENG", "iso:country": "CA", "meta:provider": ["geoplanet:7.3.1", "geoplanet:7.3.2", "geoplanet:7.4.0", "geoplanet:7.4.1", "geoplanet:7.5.1", "geoplanet:7.5.2", "geoplanet:7.6.0", "geoplanet:7.8.1", "geoplanet:7.9.0", "geoplanet:7.10.0", "geoplanet:8.0.0", "woeplanet:8.0.0"], "meta:indexed": "2020-08-20T20:29:28.243760", "meta:updated": "2020-08-22T02:31:16.493934", "woe:hierarchy": {"continent": 24865672, "country": 23424775, "town": 0, "planet": 1, "county": 29375237, "suburb": 0, "state": 2344916, "region": 0, "localadmin": 0}, "woe:timezone_id": 56043689, "woe:hash": "c3hgf4us5kuj", "woe:centroid": [-116.976097, 51.299999], "geom:latitude": 51.299999, "geom:longitude": -116.976097, "geom:hash": "c3hgf4us5kuj", "woe:latitude": 51.299999, "geom:centroid": [-116.976097, 51.299999], "woe:longitude": -116.976097, "woe:repo": "woeplanet-airport-ca"}, "geometry": {"coordinates": [-116.976097, 51.299999], "type": "Point"}}