{"type": "Feature", "id": 12524055, "properties": {"woe:id": 12524055, "woe:parent_id": 1247, "woe:name": "Killineq Airport", "woe:placetype": 14, "woe:placetype_name": "Airport", "woe:lang": "ENG", "iso:country": "CA", "meta:provider": ["geoplanet:7.3.1", "geoplanet:7.3.2", "geoplanet:7.4.0", "geoplanet:7.4.1", "geoplanet:7.5.1", "geoplanet:7.5.2", "geoplanet:7.6.0", "geoplanet:7.8.1", "geoplanet:7.9.0", "geoplanet:7.10.0", "geoplanet:8.0.0", "woeplanet:8.0.0"], "meta:indexed": "2020-08-20T20:29:28.368456", "woe:alias_ENG_V": ["XBW", "XBW Airport"], "meta:updated": "2020-08-22T02:31:16.553532", "woe:hierarchy": {"continent": 24865672, "country": 23424775, "town": 0, "planet": 1, "county": 29375189, "suburb": 0, "state": 2344922, "region": 0, "localadmin": 0}, "woe:timezone_id": 56043697, "woe:hash": "dpwd8uve433g", "woe:centroid": [-80.818764, 42.653568], "geom:latitude": 42.653568, "geom:longitude": -80.818764, "geom:hash": "dpwd8uve433g", "woe:latitude": 42.653568, "geom:centroid": [-80.818764, 42.653568], "woe:longitude": -80.818764, "woe:repo": "woeplanet-airport-ca"}, "geometry": {"coordinates": [-80.818764, 42.653568], "type": "Point"}}