{"type": "Feature", "id": 12511723, "properties": {"woe:id": 12511723, "woe:parent_id": 23395599, "woe:name": "La Sarre Airport", "woe:placetype": 14, "woe:placetype_name": "Airport", "woe:lang": "ENG", "iso:country": "CA", "meta:provider": ["geoplanet:7.3.1", "geoplanet:7.3.2", "geoplanet:7.4.0", "geoplanet:7.4.1", "geoplanet:7.5.1", "geoplanet:7.5.2", "geoplanet:7.6.0", "geoplanet:7.8.1", "geoplanet:7.9.0", "geoplanet:7.10.0", "geoplanet:8.0.0", "woeplanet:8.0.0"], "meta:indexed": "2020-08-20T20:29:28.263469", "meta:updated": "2020-08-22T02:31:16.503799", "woe:hierarchy": {"continent": 24865672, "country": 23424775, "town": 0, "planet": 1, "county": 29375241, "suburb": 0, "state": 2344924, "region": 0, "localadmin": 0}, "woe:timezone_id": 56043679, "woe:hash": "f0xwq1wgsk8f", "woe:centroid": [-79.18, 48.919998], "geom:latitude": 48.919998, "geom:longitude": -79.18, "geom:hash": "f0xwq1wgsk8f", "woe:latitude": 48.919998, "geom:centroid": [-79.18, 48.919998], "woe:longitude": -79.18, "woe:repo": "woeplanet-airport-ca"}, "geometry": {"coordinates": [-79.18, 48.919998], "type": "Point"}}