{"type": "Feature", "id": 12511660, "properties": {"woe:id": 12511660, "woe:parent_id": 8191, "woe:name": "Foremost Airport", "woe:placetype": 14, "woe:placetype_name": "Airport", "woe:lang": "ENG", "iso:country": "CA", "meta:provider": ["geoplanet:7.3.1", "geoplanet:7.3.2", "geoplanet:7.4.0", "geoplanet:7.4.1", "geoplanet:7.5.1", "geoplanet:7.5.2", "geoplanet:7.6.0", "geoplanet:7.8.1", "geoplanet:7.9.0", "geoplanet:7.10.0", "geoplanet:8.0.0", "woeplanet:8.0.0"], "meta:indexed": "2020-08-20T20:29:28.235833", "meta:updated": "2020-08-22T02:31:16.490964", "woe:hierarchy": {"continent": 24865672, "country": 23424775, "town": 0, "planet": 1, "county": 29375228, "suburb": 0, "state": 2344915, "region": 0, "localadmin": 0}, "woe:timezone_id": 56043686, "woe:hash": "c8b9wbhgfydg", "woe:centroid": [-111.493599, 49.483101], "geom:latitude": 49.483101, "geom:longitude": -111.493599, "geom:hash": "c8b9wbhgfydg", "woe:latitude": 49.483101, "geom:centroid": [-111.493599, 49.483101], "woe:longitude": -111.493599, "woe:repo": "woeplanet-airport-ca"}, "geometry": {"coordinates": [-111.493599, 49.483101], "type": "Point"}}