{"type": "Feature", "id": 12511705, "geometry": {"type": "Point", "coordinates": [-133.497223, 68.306427]}, "properties": {"woe:id": 12511705, "woe:parent_id": 4251, "woe:name": "Inuvik Airport", "woe:placetype": 14, "woe:placetype_name": "Airport", "woe:lang": "ENG", "iso:country": "CA", "meta:provider": ["geoplanet:7.3.1", "geoplanet:7.3.2", "geoplanet:7.4.0", "geoplanet:7.4.1", "geoplanet:7.5.1", "geoplanet:7.5.2", "geoplanet:7.6.0", "geoplanet:7.8.1", "geoplanet:7.9.0", "geoplanet:7.10.0", "geoplanet:8.0.0", "woeplanet:8.0.0"], "meta:indexed": "2020-08-20T20:29:28.681160", "woe:alias_ENG_V": ["YEV", "YEV Airport"], "meta:updated": "2020-10-14T12:10:35.523131", "woe:hierarchy": {"continent": 24865672, "country": 23424775, "town": 0, "planet": 1, "county": 29375229, "suburb": 0, "state": 2344920, "region": 0, "localadmin": 0}, "woe:timezone_id": 56043692, "woe:hash": "ch1hd4y3c0zs", "woe:centroid": [-133.497223, 68.306427], "geom:latitude": 68.306427, "geom:longitude": -133.497223, "geom:hash": "ch1hd4y3c0zs", "woe:latitude": 68.306427, "geom:centroid": [-133.497223, 68.306427], "woe:longitude": -133.497223, "woe:repo": "woeplanet-airport-ca", "geom:area": 0.0, "woe:scale": 19}}