{"type": "Feature", "id": 12524066, "properties": {"woe:id": 12524066, "woe:parent_id": 2551, "woe:name": "Poplar River Airport", "woe:placetype": 14, "woe:placetype_name": "Airport", "woe:lang": "ENG", "iso:country": "CA", "meta:provider": ["geoplanet:7.3.1", "geoplanet:7.3.2", "geoplanet:7.4.0", "geoplanet:7.4.1", "geoplanet:7.5.1", "geoplanet:7.5.2", "geoplanet:7.6.0", "geoplanet:7.8.1", "geoplanet:7.9.0", "geoplanet:7.10.0", "geoplanet:8.0.0", "woeplanet:8.0.0"], "meta:indexed": "2020-08-20T20:29:28.376415", "woe:alias_ENG_V": ["XPP", "XPP Airport"], "meta:updated": "2020-08-22T02:31:16.557218", "woe:hierarchy": {"continent": 24865672, "country": 23424775, "town": 0, "planet": 1, "county": 29375231, "suburb": 0, "state": 2344917, "region": 0, "localadmin": 0}, "woe:timezone_id": 56043674, "woe:hash": "cc6v3kgz81vb", "woe:centroid": [-97.322723, 52.981491], "geom:latitude": 52.981491, "geom:longitude": -97.322723, "geom:hash": "cc6v3kgz81vb", "woe:latitude": 52.981491, "geom:centroid": [-97.322723, 52.981491], "woe:longitude": -97.322723, "woe:repo": "woeplanet-airport-ca"}, "geometry": {"coordinates": [-97.322723, 52.981491], "type": "Point"}}