{"type": "Feature", "id": 12524041, "properties": {"woe:id": 12524041, "woe:parent_id": 24609740, "woe:name": "Taltheilei Narrows Airport", "woe:placetype": 14, "woe:placetype_name": "Airport", "woe:lang": "ENG", "iso:country": "CA", "meta:provider": ["geoplanet:7.3.1", "geoplanet:7.3.2", "geoplanet:7.4.0", "geoplanet:7.4.1", "geoplanet:7.5.1", "geoplanet:7.5.2", "geoplanet:7.6.0", "geoplanet:7.8.1", "geoplanet:7.9.0", "geoplanet:7.10.0", "geoplanet:8.0.0", "woeplanet:8.0.0"], "meta:indexed": "2020-08-20T20:29:28.359640", "woe:alias_ENG_V": ["GSL", "GSL Airport"], "meta:updated": "2020-08-22T02:31:16.547981", "woe:hierarchy": {"continent": 24865672, "country": 23424775, "town": 0, "planet": 1, "county": 29375229, "suburb": 0, "state": 2344920, "region": 0, "localadmin": 0}, "woe:timezone_id": 56043691, "woe:hash": "ce0sjg6r476n", "woe:centroid": [-111.541, 62.597198], "geom:latitude": 62.597198, "geom:longitude": -111.541, "geom:hash": "ce0sjg6r476n", "woe:latitude": 62.597198, "geom:centroid": [-111.541, 62.597198], "woe:longitude": -111.541, "woe:repo": "woeplanet-airport-ca"}, "geometry": {"coordinates": [-111.541, 62.597198], "type": "Point"}}