{"type": "Feature", "id": 12511626, "geometry": {"type": "Point", "coordinates": [-74.559982, 45.09198]}, "properties": {"woe:id": 12511626, "woe:parent_id": 23399237, "woe:name": "Cornwall Regional Airport", "woe:placetype": 14, "woe:placetype_name": "Airport", "woe:lang": "ENG", "iso:country": "CA", "meta:provider": ["geoplanet:7.3.1", "geoplanet:7.3.2", "geoplanet:7.4.0", "geoplanet:7.4.1", "geoplanet:7.5.1", "geoplanet:7.5.2", "geoplanet:7.6.0", "geoplanet:7.8.1", "geoplanet:7.9.0", "geoplanet:7.10.0", "geoplanet:8.0.0", "woeplanet:8.0.0"], "meta:indexed": "2020-08-20T20:29:28.621234", "woe:alias_ENG_V": ["YCC", "Cornwall Airport", "Cornwall Regional", "YCC Airport"], "meta:updated": "2020-10-14T12:10:35.585799", "woe:hierarchy": {"continent": 24865672, "country": 23424775, "town": 0, "planet": 1, "county": 29375251, "suburb": 0, "state": 2344922, "region": 0, "localadmin": 0}, "woe:timezone_id": 56043697, "woe:hash": "f24bx2epf6rf", "woe:centroid": [-74.559982, 45.09198], "geom:latitude": 45.09198, "geom:longitude": -74.559982, "geom:hash": "f24bx2epf6rf", "woe:latitude": 45.09198, "geom:centroid": [-74.559982, 45.09198], "woe:longitude": -74.559982, "woe:repo": "woeplanet-airport-ca", "geom:area": 0.0, "woe:scale": 19}}