{"type": "Feature", "id": 12524211, "geometry": {"type": "Point", "coordinates": [-58.414089, 54.210209]}, "properties": {"woe:id": 12524211, "woe:parent_id": 2730, "woe:name": "Rigolet Aerodrome", "woe:placetype": 14, "woe:placetype_name": "Airport", "woe:lang": "ENG", "iso:country": "CA", "meta:provider": ["geoplanet:7.3.1", "geoplanet:7.3.2", "geoplanet:7.4.0", "geoplanet:7.4.1", "geoplanet:7.5.1", "geoplanet:7.5.2", "geoplanet:7.6.0", "geoplanet:7.8.1", "geoplanet:7.9.0", "geoplanet:7.10.0", "geoplanet:8.0.0", "woeplanet:8.0.0"], "meta:indexed": "2020-08-20T20:29:28.484327", "woe:alias_ENG_V": ["YRG", "YRG Airport"], "meta:updated": "2020-10-14T12:10:35.287165", "woe:hierarchy": {"continent": 24865672, "country": 23424775, "town": 0, "planet": 1, "county": 29375216, "suburb": 0, "state": 2344919, "region": 0, "localadmin": 0}, "woe:timezone_id": 56043673, "woe:hash": "f9wkqu8jm56k", "woe:centroid": [-58.414089, 54.210209], "geom:latitude": 54.210209, "geom:longitude": -58.414089, "geom:hash": "f9wkqu8jm56k", "woe:latitude": 54.210209, "geom:centroid": [-58.414089, 54.210209], "woe:longitude": -58.414089, "woe:repo": "woeplanet-airport-ca", "geom:area": 0.0, "woe:scale": 19}}