{"type": "Feature", "id": 12511719, "properties": {"woe:id": 12511719, "woe:parent_id": 781, "woe:name": "Kuujjuaq Airport", "woe:placetype": 14, "woe:placetype_name": "Airport", "woe:lang": "ENG", "iso:country": "CA", "meta:provider": ["geoplanet:7.3.1", "geoplanet:7.3.2", "geoplanet:7.4.0", "geoplanet:7.4.1", "geoplanet:7.5.1", "geoplanet:7.5.2", "geoplanet:7.6.0", "geoplanet:7.8.1", "geoplanet:7.9.0", "geoplanet:7.10.0", "geoplanet:8.0.0", "woeplanet:8.0.0"], "meta:indexed": "2020-08-20T20:29:28.261072", "woe:alias_ENG_V": ["YVP", "YVP Airport"], "meta:updated": "2020-08-22T02:31:16.502526", "woe:hierarchy": {"continent": 24865672, "country": 23424775, "town": 0, "planet": 1, "county": 29375254, "suburb": 0, "state": 2344924, "region": 0, "localadmin": 0}, "woe:timezone_id": 56043679, "woe:hash": "f6r6dc0k7w1v", "woe:centroid": [-68.433342, 58.101959], "geom:latitude": 58.101959, "geom:longitude": -68.433342, "geom:hash": "f6r6dc0k7w1v", "woe:latitude": 58.101959, "geom:centroid": [-68.433342, 58.101959], "woe:longitude": -68.433342, "woe:repo": "woeplanet-airport-ca"}, "geometry": {"coordinates": [-68.433342, 58.101959], "type": "Point"}}