{"type": "Feature", "id": 12511759, "geometry": {"type": "Point", "coordinates": [-73.430313, 45.508598]}, "properties": {"woe:id": 12511759, "woe:parent_id": 23396696, "woe:name": "A\u00e9roport de St-Hubert", "woe:placetype": 14, "woe:placetype_name": "Airport", "woe:lang": "FRE", "iso:country": "CA", "meta:provider": ["geoplanet:7.4.0", "geoplanet:7.4.1", "geoplanet:7.5.1", "geoplanet:7.5.2", "geoplanet:7.6.0", "geoplanet:7.8.1", "geoplanet:7.9.0", "geoplanet:7.10.0", "geoplanet:8.0.0", "woeplanet:8.0.0"], "meta:indexed": "2020-08-21T00:01:10.494115", "woe:alias_ENG_V": ["Montreal St Hubert", "YHU Airport", "St Hubert Airport", "YHU"], "woe:alias_ENG_P": ["Montreal St Hubert Airport"], "meta:updated": "2020-10-14T12:10:35.467490", "woe:alias_FRE_S": ["Aeroport de Saint-Hubert", "Aeroport de St-Hubert"], "woe:alias_FRE_V": ["Aeroport d\u00e9 Saint-Hubert"], "woe:hierarchy": {"continent": 24865672, "country": 23424775, "town": 0, "planet": 1, "county": 29375100, "suburb": 0, "state": 2344924, "region": 0, "localadmin": 0}, "woe:timezone_id": 56043679, "woe:hash": "f25fch9dv9w1", "woe:centroid": [-73.430313, 45.508598], "geom:latitude": 45.508598, "geom:longitude": -73.430313, "geom:hash": "f25fch9dv9w1", "woe:latitude": 45.508598, "geom:centroid": [-73.430313, 45.508598], "woe:longitude": -73.430313, "woe:repo": "woeplanet-airport-ca", "geom:area": 0.0, "woe:scale": 19}}