{"type": "Feature", "id": 12511696, "properties": {"woe:id": 12511696, "woe:parent_id": 8791, "woe:name": "High River Airport", "woe:placetype": 14, "woe:placetype_name": "Airport", "woe:lang": "ENG", "iso:country": "CA", "meta:provider": ["geoplanet:7.3.1", "geoplanet:7.3.2", "geoplanet:7.4.0", "geoplanet:7.4.1", "geoplanet:7.5.1", "geoplanet:7.5.2", "geoplanet:7.6.0", "geoplanet:7.8.1", "geoplanet:7.9.0", "geoplanet:7.10.0", "geoplanet:8.0.0", "woeplanet:8.0.0"], "meta:indexed": "2020-08-20T20:29:28.252985", "meta:updated": "2020-08-22T02:31:16.497615", "woe:hierarchy": {"continent": 24865672, "country": 23424775, "town": 0, "planet": 1, "county": 29375228, "suburb": 0, "state": 2344915, "region": 0, "localadmin": 0}, "woe:timezone_id": 56043689, "woe:hash": "c2zp3rr1b1t2", "woe:centroid": [-113.841698, 50.533298], "geom:latitude": 50.533298, "geom:longitude": -113.841698, "geom:hash": "c2zp3rr1b1t2", "woe:latitude": 50.533298, "geom:centroid": [-113.841698, 50.533298], "woe:longitude": -113.841698, "woe:repo": "woeplanet-airport-ca"}, "geometry": {"coordinates": [-113.841698, 50.533298], "type": "Point"}}