{"type": "Feature", "id": 12523339, "geometry": {"type": "Point", "coordinates": [-79.346619, 43.638191]}, "properties": {"woe:id": 12523339, "woe:parent_id": 55855853, "woe:name": "Toronto Downtown Airport", "woe:placetype": 14, "woe:placetype_name": "Airport", "woe:lang": "ENG", "iso:country": "CA", "meta:provider": ["geoplanet:7.3.1", "geoplanet:7.3.2", "geoplanet:7.4.0", "geoplanet:7.4.1", "geoplanet:7.5.1", "geoplanet:7.5.2", "geoplanet:7.6.0", "geoplanet:7.8.1", "geoplanet:7.9.0", "geoplanet:7.10.0", "geoplanet:8.0.0", "woeplanet:8.0.0"], "meta:indexed": "2020-08-20T20:29:28.356514", "woe:alias_ENG_V": ["YBZ", "Toronto Downtown", "YBZ Airport"], "meta:updated": "2020-10-14T12:10:35.454344", "woe:hierarchy": {"continent": 24865672, "country": 23424775, "town": 0, "planet": 1, "county": 29375205, "suburb": 0, "state": 2344922, "region": 0, "localadmin": 0}, "woe:timezone_id": 56043697, "woe:hash": "dpz862jdcu2s", "woe:centroid": [-79.346619, 43.638191], "geom:latitude": 43.638191, "geom:longitude": -79.346619, "geom:hash": "dpz862jdcu2s", "woe:latitude": 43.638191, "geom:centroid": [-79.346619, 43.638191], "woe:longitude": -79.346619, "woe:repo": "woeplanet-airport-ca", "geom:area": 0.0, "woe:scale": 19}}