{"type": "Feature", "id": 12511765, "properties": {"woe:id": 12511765, "woe:parent_id": 4107, "woe:name": "Mountain View Airport", "woe:placetype": 14, "woe:placetype_name": "Airport", "woe:lang": "ENG", "iso:country": "CA", "meta:provider": ["geoplanet:7.3.1", "geoplanet:7.3.2", "geoplanet:7.4.0", "geoplanet:7.4.1", "geoplanet:7.5.1", "geoplanet:7.5.2", "geoplanet:7.6.0", "geoplanet:7.8.1", "geoplanet:7.9.0", "geoplanet:7.10.0", "geoplanet:8.0.0", "woeplanet:8.0.0"], "meta:indexed": "2020-08-20T20:29:28.281475", "woe:alias_ENG_V": ["Mtn View Airport"], "meta:updated": "2020-08-22T02:31:16.510578", "woe:hierarchy": {"continent": 24865672, "country": 23424775, "town": 0, "planet": 1, "county": 29375058, "suburb": 0, "state": 2344922, "region": 0, "localadmin": 0}, "woe:timezone_id": 56043697, "woe:hash": "drc48pke3ddy", "woe:centroid": [-77.337502, 44.073601], "geom:latitude": 44.073601, "geom:longitude": -77.337502, "geom:hash": "drc48pke3ddy", "woe:latitude": 44.073601, "geom:centroid": [-77.337502, 44.073601], "woe:longitude": -77.337502, "woe:repo": "woeplanet-airport-ca"}, "geometry": {"coordinates": [-77.337502, 44.073601], "type": "Point"}}