{"type": "Feature", "id": 12524151, "properties": {"woe:id": 12524151, "woe:parent_id": 9129, "woe:name": "Johnny Mountain Airport", "woe:placetype": 14, "woe:placetype_name": "Airport", "woe:lang": "ENG", "iso:country": "CA", "meta:provider": ["geoplanet:7.3.1", "geoplanet:7.3.2", "geoplanet:7.4.0", "geoplanet:7.4.1", "geoplanet:7.5.1", "geoplanet:7.5.2", "geoplanet:7.6.0", "geoplanet:7.8.1", "geoplanet:7.9.0", "geoplanet:7.10.0", "geoplanet:8.0.0", "woeplanet:8.0.0"], "meta:indexed": "2020-08-20T20:29:28.441398", "woe:alias_ENG_V": ["YJO", "YJO Airport"], "meta:updated": "2020-08-22T02:31:16.582670", "woe:hierarchy": {"continent": 24865672, "country": 23424775, "town": 0, "planet": 1, "county": 29375209, "suburb": 0, "state": 2344916, "region": 0, "localadmin": 0}, "woe:timezone_id": 56043690, "woe:hash": "c44f27ge2q5s", "woe:centroid": [-131.117004, 56.666698], "geom:latitude": 56.666698, "geom:longitude": -131.117004, "geom:hash": "c44f27ge2q5s", "woe:latitude": 56.666698, "geom:centroid": [-131.117004, 56.666698], "woe:longitude": -131.117004, "woe:repo": "woeplanet-airport-ca"}, "geometry": {"coordinates": [-131.117004, 56.666698], "type": "Point"}}