{"type": "Feature", "id": 12524093, "geometry": {"type": "Point", "coordinates": [-90.734032, 63.335812]}, "properties": {"woe:id": 12524093, "woe:parent_id": 4308, "woe:name": "Chesterfield Inlet Airport", "woe:placetype": 14, "woe:placetype_name": "Airport", "woe:lang": "ENG", "iso:country": "CA", "meta:provider": ["geoplanet:7.3.1", "geoplanet:7.3.2", "geoplanet:7.4.0", "geoplanet:7.4.1", "geoplanet:7.5.1", "geoplanet:7.5.2", "geoplanet:7.6.0", "geoplanet:7.8.1", "geoplanet:7.9.0", "geoplanet:7.10.0", "geoplanet:8.0.0", "woeplanet:8.0.0"], "meta:indexed": "2020-08-20T20:29:28.400742", "woe:alias_ENG_V": ["YCS", "YCS Airport"], "meta:updated": "2020-10-14T12:10:35.356617", "woe:hierarchy": {"continent": 24865672, "country": 23424775, "town": 0, "planet": 1, "county": 29375230, "suburb": 0, "state": 20069920, "region": 0, "localadmin": 0}, "woe:timezone_id": 56043698, "woe:hash": "cgr2r3cmzg45", "woe:centroid": [-90.734032, 63.335812], "geom:latitude": 63.335812, "geom:longitude": -90.734032, "geom:hash": "cgr2r3cmzg45", "woe:latitude": 63.335812, "geom:centroid": [-90.734032, 63.335812], "woe:longitude": -90.734032, "woe:repo": "woeplanet-airport-ca", "geom:area": 0.0, "woe:scale": 19}}