{"type": "Feature", "id": 12511918, "geometry": {"type": "Point", "coordinates": [-97.22641, 49.903191]}, "properties": {"woe:id": 12511918, "woe:parent_id": 55856066, "woe:name": "Winnipeg International Airport", "woe:placetype": 14, "woe:placetype_name": "Airport", "woe:lang": "ENG", "iso:country": "CA", "meta:provider": ["geoplanet:7.3.1", "geoplanet:7.3.2", "geoplanet:7.4.0", "geoplanet:7.4.1", "geoplanet:7.5.1", "geoplanet:7.5.2", "geoplanet:7.6.0", "geoplanet:7.8.1", "geoplanet:7.9.0", "geoplanet:7.10.0", "geoplanet:8.0.0", "woeplanet:8.0.0"], "meta:indexed": "2020-08-20T20:29:28.684264", "woe:alias_ENG_V": ["James A Richardson Int'l Airport", "Winnipeg James A Richardson Int'l", "YWG", "Winnipeg Airport", "Winnipeg International", "YWG Airport"], "woe:alias_FRE_Q": ["A\u00e9roport International de Winnipeg"], "meta:updated": "2020-10-14T12:10:35.439320", "woe:alias_FRE_S": ["Aeroport International de Winnipeg", "Aeroport Int'l James-A-Richardson"], "woe:alias_FRE_V": ["A\u00e9roport Int'l James-A-Richardson"], "woe:hierarchy": {"continent": 24865672, "country": 23424775, "town": 0, "planet": 1, "county": 29375231, "suburb": 0, "state": 2344917, "region": 0, "localadmin": 0}, "woe:timezone_id": 56043674, "woe:hash": "cbfggs9ghmn1", "woe:centroid": [-97.22641, 49.903191], "geom:latitude": 49.903191, "geom:longitude": -97.22641, "geom:hash": "cbfggs9ghmn1", "woe:latitude": 49.903191, "geom:centroid": [-97.22641, 49.903191], "woe:longitude": -97.22641, "woe:repo": "woeplanet-airport-ca", "geom:area": 0.0, "woe:scale": 19}}