{"type": "Feature", "id": 12524221, "geometry": {"type": "Point", "coordinates": [-59.77079, 54.911919]}, "properties": {"woe:id": 12524221, "woe:parent_id": 2727, "woe:name": "Postville Aerodrome", "woe:placetype": 14, "woe:placetype_name": "Airport", "woe:lang": "ENG", "iso:country": "CA", "meta:provider": ["geoplanet:7.3.1", "geoplanet:7.3.2", "geoplanet:7.4.0", "geoplanet:7.4.1", "geoplanet:7.5.1", "geoplanet:7.5.2", "geoplanet:7.6.0", "geoplanet:7.8.1", "geoplanet:7.9.0", "geoplanet:7.10.0", "geoplanet:8.0.0", "woeplanet:8.0.0"], "meta:indexed": "2020-08-20T20:29:28.490955", "woe:alias_ENG_V": ["YSO", "YSO Airport"], "meta:updated": "2020-10-14T12:10:35.287753", "woe:hierarchy": {"continent": 24865672, "country": 23424775, "town": 0, "planet": 1, "county": 29375216, "suburb": 0, "state": 2344919, "region": 0, "localadmin": 0}, "woe:timezone_id": 56043673, "woe:hash": "f9v2rukjpese", "woe:centroid": [-59.77079, 54.911919], "geom:latitude": 54.911919, "geom:longitude": -59.77079, "geom:hash": "f9v2rukjpese", "woe:latitude": 54.911919, "geom:centroid": [-59.77079, 54.911919], "woe:longitude": -59.77079, "woe:repo": "woeplanet-airport-ca", "geom:area": 0.0, "woe:scale": 19}}