{"type": "Feature", "id": 12523277, "geometry": {"type": "Point", "coordinates": [-122.949997, 50.133331]}, "properties": {"woe:id": 12523277, "woe:parent_id": 23405148, "woe:name": "Green Lake Water Aerodrome", "woe:placetype": 14, "woe:placetype_name": "Airport", "woe:lang": "ENG", "iso:country": "CA", "meta:provider": ["geoplanet:7.3.1", "geoplanet:7.3.2", "geoplanet:7.4.0", "geoplanet:7.4.1", "geoplanet:7.5.1", "geoplanet:7.5.2", "geoplanet:7.6.0", "geoplanet:7.8.1", "geoplanet:7.9.0", "geoplanet:7.10.0", "geoplanet:8.0.0", "woeplanet:8.0.0"], "meta:indexed": "2020-08-20T20:29:28.351899", "woe:alias_ENG_V": ["YWS", "YWS Airport"], "meta:updated": "2020-10-14T12:10:35.428493", "woe:hierarchy": {"continent": 24865672, "country": 23424775, "town": 0, "planet": 1, "county": 29375187, "suburb": 0, "state": 2344916, "region": 0, "localadmin": 0}, "woe:timezone_id": 56043690, "woe:hash": "c2bt4nqxc6m2", "woe:centroid": [-122.949997, 50.133331], "geom:latitude": 50.133331, "geom:longitude": -122.949997, "geom:hash": "c2bt4nqxc6m2", "woe:latitude": 50.133331, "geom:centroid": [-122.949997, 50.133331], "woe:longitude": -122.949997, "woe:repo": "woeplanet-airport-ca", "geom:area": 0.0, "woe:scale": 19}}