{"type": "Feature", "id": 12524090, "properties": {"woe:id": 12524090, "woe:parent_id": 29374027, "woe:name": "Colville Lake Airport", "woe:placetype": 14, "woe:placetype_name": "Airport", "woe:lang": "ENG", "iso:country": "CA", "meta:provider": ["geoplanet:7.3.1", "geoplanet:7.3.2", "geoplanet:7.4.0", "geoplanet:7.4.1", "geoplanet:7.5.1", "geoplanet:7.5.2", "geoplanet:7.6.0", "geoplanet:7.8.1", "geoplanet:7.9.0", "geoplanet:7.10.0", "geoplanet:8.0.0", "woeplanet:8.0.0"], "meta:indexed": "2020-08-20T20:29:28.397866", "woe:alias_ENG_V": ["YCK", "YCK Airport"], "meta:updated": "2020-08-22T02:31:16.563644", "woe:hierarchy": {"continent": 24865672, "country": 23424775, "town": 0, "planet": 1, "county": 29375229, "suburb": 0, "state": 2344920, "region": 0, "localadmin": 0}, "woe:timezone_id": 56043691, "woe:hash": "c5yt2jhrxudn", "woe:centroid": [-125.853203, 67.04538], "geom:latitude": 67.04538, "geom:longitude": -125.853203, "geom:hash": "c5yt2jhrxudn", "woe:latitude": 67.04538, "geom:centroid": [-125.853203, 67.04538], "woe:longitude": -125.853203, "woe:repo": "woeplanet-airport-ca"}, "geometry": {"coordinates": [-125.853203, 67.04538], "type": "Point"}}