{"type": "Feature", "id": 12524059, "properties": {"woe:id": 12524059, "woe:parent_id": 23394707, "woe:name": "Kangiqsualujjuaq Airport", "woe:placetype": 14, "woe:placetype_name": "Airport", "woe:lang": "ENG", "iso:country": "CA", "meta:provider": ["geoplanet:7.3.1", "geoplanet:7.3.2", "geoplanet:7.4.0", "geoplanet:7.4.1", "geoplanet:7.5.1", "geoplanet:7.5.2", "geoplanet:7.6.0", "geoplanet:7.8.1", "geoplanet:7.9.0", "geoplanet:7.10.0", "geoplanet:8.0.0", "woeplanet:8.0.0"], "meta:indexed": "2020-08-20T20:29:28.370458", "woe:alias_ENG_V": ["XGR", "XGR Airport"], "meta:updated": "2020-08-22T02:31:16.554793", "woe:hierarchy": {"continent": 24865672, "country": 23424775, "town": 0, "planet": 1, "county": 29375254, "suburb": 0, "state": 2344924, "region": 0, "localadmin": 0}, "woe:timezone_id": 56043679, "woe:hash": "fd3huxugxqc2", "woe:centroid": [-65.88916, 58.53442], "geom:latitude": 58.53442, "geom:longitude": -65.88916, "geom:hash": "fd3huxugxqc2", "woe:latitude": 58.53442, "geom:centroid": [-65.88916, 58.53442], "woe:longitude": -65.88916, "woe:repo": "woeplanet-airport-ca"}, "geometry": {"coordinates": [-65.88916, 58.53442], "type": "Point"}}