{"type": "Feature", "id": 12524099, "properties": {"woe:id": 12524099, "woe:parent_id": 2739, "woe:name": "Paradise River Airport", "woe:placetype": 14, "woe:placetype_name": "Airport", "woe:lang": "ENG", "iso:country": "CA", "meta:provider": ["geoplanet:7.3.1", "geoplanet:7.3.2", "geoplanet:7.4.0", "geoplanet:7.4.1", "geoplanet:7.5.1", "geoplanet:7.5.2", "geoplanet:7.6.0", "geoplanet:7.8.1", "geoplanet:7.9.0", "geoplanet:7.10.0", "geoplanet:8.0.0", "woeplanet:8.0.0"], "meta:indexed": "2020-08-20T20:29:28.403822", "woe:alias_ENG_V": ["YDE", "YDE Airport"], "meta:updated": "2020-08-22T02:31:16.565848", "woe:hierarchy": {"continent": 24865672, "country": 23424775, "town": 0, "planet": 1, "county": 29375216, "suburb": 0, "state": 2344919, "region": 0, "localadmin": 0}, "woe:timezone_id": 56043673, "woe:hash": "f9rrcx5zx3p4", "woe:centroid": [-57.233299, 53.4333], "geom:latitude": 53.4333, "geom:longitude": -57.233299, "geom:hash": "f9rrcx5zx3p4", "woe:latitude": 53.4333, "geom:centroid": [-57.233299, 53.4333], "woe:longitude": -57.233299, "woe:repo": "woeplanet-airport-ca"}, "geometry": {"coordinates": [-57.233299, 53.4333], "type": "Point"}}