{"type": "Feature", "id": 12511787, "properties": {"woe:id": 12511787, "woe:parent_id": 3314, "woe:name": "Pembroke Airport", "woe:placetype": 14, "woe:placetype_name": "Airport", "woe:lang": "ENG", "iso:country": "CA", "meta:provider": ["geoplanet:7.3.1", "geoplanet:7.3.2", "geoplanet:7.4.0", "geoplanet:7.4.1", "geoplanet:7.5.1", "geoplanet:7.5.2", "geoplanet:7.6.0", "geoplanet:7.8.1", "geoplanet:7.9.0", "geoplanet:7.10.0", "geoplanet:8.0.0", "woeplanet:8.0.0"], "meta:indexed": "2020-08-20T20:29:28.685798", "woe:alias_ENG_V": ["Pembroke & Area Municipal Airport", "YTA", "YTA Airport"], "meta:updated": "2020-08-22T02:31:16.715403", "woe:hierarchy": {"continent": 24865672, "country": 23424775, "town": 0, "planet": 1, "county": 29375220, "suburb": 0, "state": 2344922, "region": 0, "localadmin": 0}, "woe:timezone_id": 56043697, "woe:hash": "f21hcvxtccwe", "woe:centroid": [-77.256462, 45.866169], "geom:latitude": 45.866169, "geom:longitude": -77.256462, "geom:hash": "f21hcvxtccwe", "woe:latitude": 45.866169, "geom:centroid": [-77.256462, 45.866169], "woe:longitude": -77.256462, "woe:repo": "woeplanet-airport-ca"}, "geometry": {"coordinates": [-77.256462, 45.866169], "type": "Point"}}