{"type": "Feature", "id": 12511587, "properties": {"woe:id": 12511587, "woe:parent_id": 23400989, "woe:name": "Brantford Airport", "woe:placetype": 14, "woe:placetype_name": "Airport", "woe:lang": "ENG", "iso:country": "CA", "meta:provider": ["geoplanet:7.3.1", "geoplanet:7.3.2", "geoplanet:7.4.0", "geoplanet:7.4.1", "geoplanet:7.5.1", "geoplanet:7.5.2", "geoplanet:7.6.0", "geoplanet:7.8.1", "geoplanet:7.9.0", "geoplanet:7.10.0", "geoplanet:8.0.0", "woeplanet:8.0.0"], "meta:indexed": "2020-08-20T20:29:28.674436", "woe:alias_ENG_V": ["XFV"], "meta:updated": "2020-08-22T02:31:16.710103", "woe:hierarchy": {"continent": 24865672, "country": 23424775, "town": 0, "planet": 1, "county": 29375169, "suburb": 0, "state": 2344922, "region": 0, "localadmin": 0}, "woe:timezone_id": 56043697, "woe:hash": "dpwv7g4sgs3s", "woe:centroid": [-80.339432, 43.12767], "geom:latitude": 43.12767, "geom:longitude": -80.339432, "geom:hash": "dpwv7g4sgs3s", "woe:latitude": 43.12767, "geom:centroid": [-80.339432, 43.12767], "woe:longitude": -80.339432, "woe:repo": "woeplanet-airport-ca"}, "geometry": {"coordinates": [-80.339432, 43.12767], "type": "Point"}}