{"type": "Feature", "id": 12511573, "geometry": {"type": "Point", "coordinates": [-114.433296, 54.099998]}, "properties": {"woe:id": 12511573, "woe:parent_id": 29372983, "woe:name": "Barrhead Airport", "woe:placetype": 14, "woe:placetype_name": "Airport", "woe:lang": "ENG", "iso:country": "CA", "meta:provider": ["geoplanet:7.3.1", "geoplanet:7.3.2", "geoplanet:7.4.0", "geoplanet:7.4.1", "geoplanet:7.5.1", "geoplanet:7.5.2", "geoplanet:7.6.0", "geoplanet:7.8.1", "geoplanet:7.9.0", "geoplanet:7.10.0", "geoplanet:8.0.0", "woeplanet:8.0.0"], "meta:indexed": "2020-08-20T20:29:28.195430", "meta:updated": "2020-10-14T12:10:35.611758", "woe:hierarchy": {"continent": 24865672, "country": 23424775, "town": 0, "planet": 1, "county": 29375228, "suburb": 0, "state": 2344915, "region": 0, "localadmin": 0}, "woe:timezone_id": 56043689, "woe:hash": "c3weu085qfw4", "woe:centroid": [-114.433296, 54.099998], "geom:latitude": 54.099998, "geom:longitude": -114.433296, "geom:hash": "c3weu085qfw4", "woe:latitude": 54.099998, "geom:centroid": [-114.433296, 54.099998], "woe:longitude": -114.433296, "woe:repo": "woeplanet-airport-ca", "geom:area": 0.0, "woe:scale": 19}}