{"type": "Feature", "id": 12511923, "properties": {"woe:id": 12511923, "woe:parent_id": 2461, "woe:name": "Yorkton Airport", "woe:placetype": 14, "woe:placetype_name": "Airport", "woe:lang": "ENG", "iso:country": "CA", "meta:provider": ["geoplanet:7.3.1", "geoplanet:7.3.2", "geoplanet:7.4.0", "geoplanet:7.4.1", "geoplanet:7.5.1", "geoplanet:7.5.2", "geoplanet:7.6.0", "geoplanet:7.8.1", "geoplanet:7.9.0", "geoplanet:7.10.0", "geoplanet:8.0.0", "woeplanet:8.0.0"], "meta:indexed": "2020-08-20T20:29:28.646874", "woe:alias_ENG_V": ["YQV", "YQV Airport"], "meta:updated": "2020-08-22T02:31:16.698065", "woe:hierarchy": {"continent": 24865672, "country": 23424775, "town": 0, "planet": 1, "county": 29375232, "suburb": 0, "state": 2344925, "region": 0, "localadmin": 0}, "woe:timezone_id": 56043687, "woe:hash": "c9p5s7m14xug", "woe:centroid": [-102.462502, 51.258301], "geom:latitude": 51.258301, "geom:longitude": -102.462502, "geom:hash": "c9p5s7m14xug", "woe:latitude": 51.258301, "geom:centroid": [-102.462502, 51.258301], "woe:longitude": -102.462502, "woe:repo": "woeplanet-airport-ca"}, "geometry": {"coordinates": [-102.462502, 51.258301], "type": "Point"}}