{"type": "Feature", "id": 12524078, "geometry": {"type": "Point", "coordinates": [-82.392036, 52.933781]}, "properties": {"woe:id": 12524078, "woe:parent_id": 32, "woe:name": "Attawapiskat Airport", "woe:placetype": 14, "woe:placetype_name": "Airport", "woe:lang": "ENG", "iso:country": "CA", "meta:provider": ["geoplanet:7.3.1", "geoplanet:7.3.2", "geoplanet:7.4.0", "geoplanet:7.4.1", "geoplanet:7.5.1", "geoplanet:7.5.2", "geoplanet:7.6.0", "geoplanet:7.8.1", "geoplanet:7.9.0", "geoplanet:7.10.0", "geoplanet:8.0.0", "woeplanet:8.0.0"], "meta:indexed": "2020-08-20T20:29:28.385331", "woe:alias_ENG_V": ["YAT", "YAT Airport"], "meta:updated": "2020-10-14T12:10:35.322040", "woe:hierarchy": {"continent": 24865672, "country": 23424775, "town": 0, "planet": 1, "county": 29375238, "suburb": 0, "state": 2344922, "region": 0, "localadmin": 0}, "woe:timezone_id": 56043695, "woe:hash": "f1mmjh7cw7vp", "woe:centroid": [-82.392036, 52.933781], "geom:latitude": 52.933781, "geom:longitude": -82.392036, "geom:hash": "f1mmjh7cw7vp", "woe:latitude": 52.933781, "geom:centroid": [-82.392036, 52.933781], "woe:longitude": -82.392036, "woe:repo": "woeplanet-airport-ca", "geom:area": 0.0, "woe:scale": 19}}