{"type": "Feature", "id": 12524116, "properties": {"woe:id": 12524116, "woe:parent_id": 23397816, "woe:name": "Kaschechewan Airport", "woe:placetype": 14, "woe:placetype_name": "Airport", "woe:lang": "ENG", "iso:country": "CA", "meta:provider": ["geoplanet:7.3.1", "geoplanet:7.3.2", "geoplanet:7.4.0", "geoplanet:7.4.1", "geoplanet:7.5.1", "geoplanet:7.5.2", "geoplanet:7.6.0", "geoplanet:7.8.1", "geoplanet:7.9.0", "geoplanet:7.10.0", "geoplanet:8.0.0", "woeplanet:8.0.0"], "meta:indexed": "2020-08-20T20:29:28.414453", "woe:alias_ENG_V": ["ZKE", "ZKE Airport"], "meta:updated": "2020-08-22T02:31:16.570002", "woe:hierarchy": {"continent": 24865672, "country": 23424775, "town": 0, "planet": 1, "county": 29375238, "suburb": 0, "state": 2344922, "region": 0, "localadmin": 0}, "woe:timezone_id": 56043695, "woe:hash": "f1mcwgp185vw", "woe:centroid": [-81.607811, 52.31168], "geom:latitude": 52.31168, "geom:longitude": -81.607811, "geom:hash": "f1mcwgp185vw", "woe:latitude": 52.31168, "geom:centroid": [-81.607811, 52.31168], "woe:longitude": -81.607811, "woe:repo": "woeplanet-airport-ca"}, "geometry": {"coordinates": [-81.607811, 52.31168], "type": "Point"}}