{"type": "Feature", "id": 55965859, "geometry": {"type": "Point", "coordinates": [-122.625076, 49.10157]}, "properties": {"woe:id": 55965859, "woe:parent_id": 29372901, "woe:name": "Langley Municipal Airport", "woe:placetype": 14, "woe:placetype_name": "Airport", "woe:lang": "ENG", "iso:country": "CA", "meta:provider": ["geoplanet:7.3.1", "geoplanet:7.3.2", "geoplanet:7.4.0", "geoplanet:7.4.1", "geoplanet:7.5.1", "geoplanet:7.5.2", "geoplanet:7.6.0", "geoplanet:7.8.1", "geoplanet:7.9.0", "geoplanet:7.10.0", "geoplanet:8.0.0", "woeplanet:8.0.0"], "meta:indexed": "2020-08-20T20:29:28.597748", "woe:alias_ENG_V": ["YNJ"], "meta:updated": "2020-10-14T12:10:35.195582", "woe:hierarchy": {"continent": 24865672, "country": 23424775, "town": 0, "planet": 1, "county": 29375222, "suburb": 0, "state": 2344916, "region": 0, "localadmin": 0}, "woe:timezone_id": 56043690, "woe:hash": "c28z3dejksh4", "woe:centroid": [-122.625076, 49.10157], "geom:latitude": 49.10157, "geom:longitude": -122.625076, "geom:hash": "c28z3dejksh4", "woe:latitude": 49.10157, "geom:centroid": [-122.625076, 49.10157], "woe:longitude": -122.625076, "woe:repo": "woeplanet-airport-ca", "geom:area": 0.0, "woe:scale": 19}}