{"type": "Feature", "id": 12511838, "geometry": {"type": "Point", "coordinates": [-118.838303, 55.7836]}, "properties": {"woe:id": 12511838, "woe:parent_id": 8341, "woe:name": "Spirit River Airport", "woe:placetype": 14, "woe:placetype_name": "Airport", "woe:lang": "ENG", "iso:country": "CA", "meta:provider": ["geoplanet:7.3.1", "geoplanet:7.3.2", "geoplanet:7.4.0", "geoplanet:7.4.1", "geoplanet:7.5.1", "geoplanet:7.5.2", "geoplanet:7.6.0", "geoplanet:7.8.1", "geoplanet:7.9.0", "geoplanet:7.10.0", "geoplanet:8.0.0", "woeplanet:8.0.0"], "meta:indexed": "2020-08-20T20:29:28.308613", "meta:updated": "2020-10-14T12:10:35.364651", "woe:hierarchy": {"continent": 24865672, "country": 23424775, "town": 0, "planet": 1, "county": 29375228, "suburb": 0, "state": 2344915, "region": 0, "localadmin": 0}, "woe:timezone_id": 56043689, "woe:hash": "c3gmrg0e4bdx", "woe:centroid": [-118.838303, 55.7836], "geom:latitude": 55.7836, "geom:longitude": -118.838303, "geom:hash": "c3gmrg0e4bdx", "woe:latitude": 55.7836, "geom:centroid": [-118.838303, 55.7836], "woe:longitude": -118.838303, "woe:repo": "woeplanet-airport-ca", "geom:area": 0.0, "woe:scale": 19}}