{"type": "Feature", "id": 12511659, "properties": {"woe:id": 12511659, "woe:parent_id": 23388584, "woe:name": "Fogo Airport", "woe:placetype": 14, "woe:placetype_name": "Airport", "woe:lang": "ENG", "iso:country": "CA", "meta:provider": ["geoplanet:7.3.1", "geoplanet:7.3.2", "geoplanet:7.4.0", "geoplanet:7.4.1", "geoplanet:7.5.1", "geoplanet:7.5.2", "geoplanet:7.6.0", "geoplanet:7.8.1", "geoplanet:7.9.0", "geoplanet:7.10.0", "geoplanet:8.0.0", "woeplanet:8.0.0"], "meta:indexed": "2020-08-20T20:29:28.235029", "meta:updated": "2020-08-22T02:31:16.490659", "woe:hierarchy": {"continent": 24865672, "country": 23424775, "town": 0, "planet": 1, "county": 29375216, "suburb": 0, "state": 2344919, "region": 0, "localadmin": 0}, "woe:timezone_id": 56043682, "woe:hash": "fbc6mys80x1q", "woe:centroid": [-54.233299, 49.650002], "geom:latitude": 49.650002, "geom:longitude": -54.233299, "geom:hash": "fbc6mys80x1q", "woe:latitude": 49.650002, "geom:centroid": [-54.233299, 49.650002], "woe:longitude": -54.233299, "woe:repo": "woeplanet-airport-ca"}, "geometry": {"coordinates": [-54.233299, 49.650002], "type": "Point"}}