{"type": "Feature", "id": 12524134, "properties": {"woe:id": 12524134, "woe:parent_id": 2744, "woe:name": "Port Hope Simpson Aerodrome", "woe:placetype": 14, "woe:placetype_name": "Airport", "woe:lang": "ENG", "iso:country": "CA", "meta:provider": ["geoplanet:7.3.1", "geoplanet:7.3.2", "geoplanet:7.4.0", "geoplanet:7.4.1", "geoplanet:7.5.1", "geoplanet:7.5.2", "geoplanet:7.6.0", "geoplanet:7.8.1", "geoplanet:7.9.0", "geoplanet:7.10.0", "geoplanet:8.0.0", "woeplanet:8.0.0"], "meta:indexed": "2020-08-20T20:29:28.428901", "woe:alias_ENG_V": ["YHA", "Pt Hope Simpson Aerodrome", "YHA Airport"], "meta:updated": "2020-08-22T02:31:16.575735", "woe:hierarchy": {"continent": 24865672, "country": 23424775, "town": 0, "planet": 1, "county": 29375216, "suburb": 0, "state": 2344919, "region": 0, "localadmin": 0}, "woe:timezone_id": 56043682, "woe:hash": "f9rfyg7sduw0", "woe:centroid": [-56.299999, 52.533298], "geom:latitude": 52.533298, "geom:longitude": -56.299999, "geom:hash": "f9rfyg7sduw0", "woe:latitude": 52.533298, "geom:centroid": [-56.299999, 52.533298], "woe:longitude": -56.299999, "woe:repo": "woeplanet-airport-ca"}, "geometry": {"coordinates": [-56.299999, 52.533298], "type": "Point"}}