{"type": "Feature", "id": 12524280, "geometry": {"type": "Point", "coordinates": [-132.742004, 60.1731]}, "properties": {"woe:id": 12524280, "woe:parent_id": 29373876, "woe:name": "Teslin Airport", "woe:placetype": 14, "woe:placetype_name": "Airport", "woe:lang": "ENG", "iso:country": "CA", "meta:provider": ["geoplanet:7.3.1", "geoplanet:7.3.2", "geoplanet:7.4.0", "geoplanet:7.4.1", "geoplanet:7.5.1", "geoplanet:7.5.2", "geoplanet:7.6.0", "geoplanet:7.8.1", "geoplanet:7.9.0", "geoplanet:7.10.0", "geoplanet:8.0.0", "woeplanet:8.0.0"], "meta:indexed": "2020-08-20T20:29:28.538960", "woe:alias_ENG_V": ["YZW", "YZW Airport"], "meta:updated": "2020-10-14T12:10:35.295329", "woe:hierarchy": {"continent": 24865672, "country": 23424775, "town": 0, "planet": 1, "county": 29375157, "suburb": 0, "state": 2344926, "region": 0, "localadmin": 0}, "woe:timezone_id": 56043678, "woe:hash": "c49w76hjxngg", "woe:centroid": [-132.742004, 60.1731], "geom:latitude": 60.1731, "geom:longitude": -132.742004, "geom:hash": "c49w76hjxngg", "woe:latitude": 60.1731, "geom:centroid": [-132.742004, 60.1731], "woe:longitude": -132.742004, "woe:repo": "woeplanet-airport-ca", "geom:area": 0.0, "woe:scale": 19}}