{"type": "Feature", "id": 12524143, "properties": {"woe:id": 12524143, "woe:parent_id": 4224, "woe:name": "Haines Junction Airport", "woe:placetype": 14, "woe:placetype_name": "Airport", "woe:lang": "ENG", "iso:country": "CA", "meta:provider": ["geoplanet:7.3.1", "geoplanet:7.3.2", "geoplanet:7.4.0", "geoplanet:7.4.1", "geoplanet:7.5.1", "geoplanet:7.5.2", "geoplanet:7.6.0", "geoplanet:7.8.1", "geoplanet:7.9.0", "geoplanet:7.10.0", "geoplanet:8.0.0", "woeplanet:8.0.0"], "meta:indexed": "2020-08-20T20:29:28.434972", "woe:alias_ENG_V": ["YHT", "YHT Airport"], "meta:updated": "2020-08-22T02:31:16.579029", "woe:hierarchy": {"continent": 24865672, "country": 23424775, "town": 0, "planet": 1, "county": 29375157, "suburb": 0, "state": 2344926, "region": 0, "localadmin": 0}, "woe:timezone_id": 56043678, "woe:hash": "bfy1x5tce9p9", "woe:centroid": [-137.496826, 60.751911], "geom:latitude": 60.751911, "geom:longitude": -137.496826, "geom:hash": "bfy1x5tce9p9", "woe:latitude": 60.751911, "geom:centroid": [-137.496826, 60.751911], "woe:longitude": -137.496826, "woe:repo": "woeplanet-airport-ca"}, "geometry": {"coordinates": [-137.496826, 60.751911], "type": "Point"}}