{"type": "Feature", "id": 12524096, "geometry": {"type": "Point", "coordinates": [-68.516701, 70.483299]}, "properties": {"woe:id": 12524096, "woe:parent_id": 4340, "woe:name": "Clyde River Airport", "woe:placetype": 14, "woe:placetype_name": "Airport", "woe:lang": "ENG", "iso:country": "CA", "meta:provider": ["geoplanet:7.3.1", "geoplanet:7.3.2", "geoplanet:7.4.0", "geoplanet:7.4.1", "geoplanet:7.5.1", "geoplanet:7.5.2", "geoplanet:7.6.0", "geoplanet:7.8.1", "geoplanet:7.9.0", "geoplanet:7.10.0", "geoplanet:8.0.0", "woeplanet:8.0.0"], "meta:indexed": "2020-08-20T20:29:28.402592", "woe:alias_ENG_V": ["YCY", "YCY Airport"], "meta:updated": "2020-10-14T12:10:35.354921", "woe:hierarchy": {"continent": 24865672, "country": 23424775, "town": 0, "planet": 1, "county": 29375230, "suburb": 0, "state": 20069920, "region": 0, "localadmin": 0}, "woe:timezone_id": 56043693, "woe:hash": "fkx2bz5dvphz", "woe:centroid": [-68.516701, 70.483299], "geom:latitude": 70.483299, "geom:longitude": -68.516701, "geom:hash": "fkx2bz5dvphz", "woe:latitude": 70.483299, "geom:centroid": [-68.516701, 70.483299], "woe:longitude": -68.516701, "woe:repo": "woeplanet-airport-ca", "geom:area": 0.0, "woe:scale": 19}}