{"type": "Feature", "id": 12524130, "geometry": {"type": "Point", "coordinates": [-77.758331, 55.282471]}, "properties": {"woe:id": 12524130, "woe:parent_id": 23394708, "woe:name": "Kuujjuarapik Airport", "woe:placetype": 14, "woe:placetype_name": "Airport", "woe:lang": "ENG", "iso:country": "CA", "meta:provider": ["geoplanet:7.3.1", "geoplanet:7.3.2", "geoplanet:7.4.0", "geoplanet:7.4.1", "geoplanet:7.5.1", "geoplanet:7.5.2", "geoplanet:7.6.0", "geoplanet:7.8.1", "geoplanet:7.9.0", "geoplanet:7.10.0", "geoplanet:8.0.0", "woeplanet:8.0.0"], "meta:indexed": "2020-08-20T20:29:28.425637", "woe:alias_ENG_V": ["YGW", "YGW Airport"], "meta:updated": "2020-10-14T12:10:35.250634", "woe:hierarchy": {"continent": 24865672, "country": 23424775, "town": 0, "planet": 1, "county": 29375239, "suburb": 0, "state": 2344924, "region": 0, "localadmin": 0}, "woe:timezone_id": 56043679, "woe:hash": "f3bdqxf5exd0", "woe:centroid": [-77.758331, 55.282471], "geom:latitude": 55.282471, "geom:longitude": -77.758331, "geom:hash": "f3bdqxf5exd0", "woe:latitude": 55.282471, "geom:centroid": [-77.758331, 55.282471], "woe:longitude": -77.758331, "woe:repo": "woeplanet-airport-ca", "geom:area": 0.0, "woe:scale": 19}}